Workbook

Sheet 📊 Dashboard
A1: 🏢 HR ANALYTICS DASHBOARD
A2: =TEXT(TODAY(),"MMMM DD, YYYY")&" | Auto-refreshes from Employee Data" -> June 16, 2026 | Auto-refreshes from Employee Data
A4: 👥 TOTAL EMPLOYEES | F4: 📈 AVG SALARY ($) | K4: 🔄 TURNOVER RATE | P4: 📅 AVG TENURE (Yrs)
A5: ='👥 Employee Data'!B2 -> 51 | F5: ='👥 Employee Data'!B3 -> 95580.4 | K5: ='👥 Employee Data'!B4 -> 0.098039216 | P5: ='👥 Employee Data'!B5 -> 9.144
A8: 📊 HEADCOUNT BY DEPARTMENT | K8: 🎂 WORKFORCE AGE DISTRIBUTION
A9: Engineering | B9: =COUNTIF('👥 Employee Data'!D:D,A9) -> 3 | K9: 20–29 | L9: =COUNTIFS('👥 Employee Data'!G:G,">="&20,'👥 Employee Data'!G:G,"<="&29) -> 5
A10: Sales | B10: =COUNTIF('👥 Employee Data'!D:D,A10) -> 9 | K10: 30–39 | L10: =COUNTIFS('👥 Employee Data'!G:G,">="&30,'👥 Employee Data'!G:G,"<="&39) -> 16
A11: HR | B11: =COUNTIF('👥 Employee Data'!D:D,A11) -> 3 | K11: 40–49 | L11: =COUNTIFS('👥 Employee Data'!G:G,">="&40,'👥 Employee Data'!G:G,"<="&49) -> 9
A12: Finance | B12: =COUNTIF('👥 Employee Data'!D:D,A12) -> 13 | K12: 50–59 | L12: =COUNTIFS('👥 Employee Data'!G:G,">="&50,'👥 Employee Data'!G:G,"<="&59) -> 16
A13: Marketing | B13: =COUNTIF('👥 Employee Data'!D:D,A13) -> 4 | K13: 60+ | L13: =COUNTIFS('👥 Employee Data'!G:G,">="&60,'👥 Employee Data'!G:G,"<="&99) -> 4
A14: Operations | B14: =COUNTIF('👥 Employee Data'!D:D,A14) -> 4
A15: Legal | B15: =COUNTIF('👥 Employee Data'!D:D,A15) -> 8
A16: IT | B16: =COUNTIF('👥 Employee Data'!D:D,A16) -> 6
A26: 💰 SALARY BAND ANALYSIS BY DEPARTMENT | K26: ⭐ PERFORMANCE SCORE DISTRIBUTION
A27: Department | B27: Min Salary | C27: Avg Salary | D27: Max Salary | E27: Headcount | K27: Rating | L27: Count | M27: % of Total
A28: Engineering | B28: =IFERROR(minifs('👥 Employee Data'!F:F,'👥 Employee Data'!D:D,A28),0) -> 0 | C28: =IFERROR(AVERAGEIF('👥 Employee Data'!D:D,A28,'👥 Employee Data'!F:F),0) -> 116594.33 | D28: =IFERROR(maxifs('👥 Employee Data'!F:F,'👥 Employee Data'!D:D,A28),0) -> 0 | E28: =COUNTIF('👥 Employee Data'!D:D,A28) -> 3 | K28: Outstanding (5) | L28: =COUNTIF('👥 Employee Data'!I:I,5) -> 11 | M28: =IFERROR(L28/'👥 Employee Data'!B2,0) -> 0.21568627
A29: Sales | B29: =IFERROR(minifs('👥 Employee Data'!F:F,'👥 Employee Data'!D:D,A29),0) -> 0 | C29: =IFERROR(AVERAGEIF('👥 Employee Data'!D:D,A29,'👥 Employee Data'!F:F),0) -> 94772.778 | D29: =IFERROR(maxifs('👥 Employee Data'!F:F,'👥 Employee Data'!D:D,A29),0) -> 0 | E29: =COUNTIF('👥 Employee Data'!D:D,A29) -> 9 | K29: Exceeds (4) | L29: =COUNTIF('👥 Employee Data'!I:I,4) -> 19 | M29: =IFERROR(L29/'👥 Employee Data'!B2,0) -> 0.37254902
A30: HR | B30: =IFERROR(minifs('👥 Employee Data'!F:F,'👥 Employee Data'!D:D,A30),0) -> 0 | C30: =IFERROR(AVERAGEIF('👥 Employee Data'!D:D,A30,'👥 Employee Data'!F:F),0) -> 88747.333 | D30: =IFERROR(maxifs('👥 Employee Data'!F:F,'👥 Employee Data'!D:D,A30),0) -> 0 | E30: =COUNTIF('👥 Employee Data'!D:D,A30) -> 3 | K30: Meets (3) | L30: =COUNTIF('👥 Employee Data'!I:I,3) -> 16 | M30: =IFERROR(L30/'👥 Employee Data'!B2,0) -> 0.31372549
A31: Finance | B31: =IFERROR(minifs('👥 Employee Data'!F:F,'👥 Employee Data'!D:D,A31),0) -> 0 | C31: =IFERROR(AVERAGEIF('👥 Employee Data'!D:D,A31,'👥 Employee Data'!F:F),0) -> 95281.615 | D31: =IFERROR(maxifs('👥 Employee Data'!F:F,'👥 Employee Data'!D:D,A31),0) -> 0 | E31: =COUNTIF('👥 Employee Data'!D:D,A31) -> 13 | K31: Below (2) | L31: =COUNTIF('👥 Employee Data'!I:I,2) -> 3 | M31: =IFERROR(L31/'👥 Employee Data'!B2,0) -> 0.058823529
A32: Marketing | B32: =IFERROR(minifs('👥 Employee Data'!F:F,'👥 Employee Data'!D:D,A32),0) -> 0 | C32: =IFERROR(AVERAGEIF('👥 Employee Data'!D:D,A32,'👥 Employee Data'!F:F),0) -> 79126.5 | D32: =IFERROR(maxifs('👥 Employee Data'!F:F,'👥 Employee Data'!D:D,A32),0) -> 0 | E32: =COUNTIF('👥 Employee Data'!D:D,A32) -> 4 | K32: Unsatisfactory (1) | L32: =COUNTIF('👥 Employee Data'!I:I,1) -> 1 | M32: =IFERROR(L32/'👥 Employee Data'!B2,0) -> 0.019607843
A33: Operations | B33: =IFERROR(minifs('👥 Employee Data'!F:F,'👥 Employee Data'!D:D,A33),0) -> 0 | C33: =IFERROR(AVERAGEIF('👥 Employee Data'!D:D,A33,'👥 Employee Data'!F:F),0) -> 86661.75 | D33: =IFERROR(maxifs('👥 Employee Data'!F:F,'👥 Employee Data'!D:D,A33),0) -> 0 | E33: =COUNTIF('👥 Employee Data'!D:D,A33) -> 4
A34: Legal | B34: =IFERROR(minifs('👥 Employee Data'!F:F,'👥 Employee Data'!D:D,A34),0) -> 0 | C34: =IFERROR(AVERAGEIF('👥 Employee Data'!D:D,A34,'👥 Employee Data'!F:F),0) -> 106821.38 | D34: =IFERROR(maxifs('👥 Employee Data'!F:F,'👥 Employee Data'!D:D,A34),0) -> 0 | E34: =COUNTIF('👥 Employee Data'!D:D,A34) -> 8
A35: IT | B35: =IFERROR(minifs('👥 Employee Data'!F:F,'👥 Employee Data'!D:D,A35),0) -> 0 | C35: =IFERROR(AVERAGEIF('👥 Employee Data'!D:D,A35,'👥 Employee Data'!F:F),0) -> 92275.833 | D35: =IFERROR(maxifs('👥 Employee Data'!F:F,'👥 Employee Data'!D:D,A35),0) -> 0 | E35: =COUNTIF('👥 Employee Data'!D:D,A35) -> 6

Sheet 👥 Employee Data
A1: 👥 EMPLOYEE MASTER DATABASE
A2: Total Employees | B2: =COUNTA(A6:A205)-0 -> 51
A3: Avg Salary | B3: =IFERROR(AVERAGE(F6:F205),0) -> 95580.4
A4: Turnover Rate | B4: =IFERROR(COUNTIF(K6:K205,"Inactive")/COUNTA(A6:A205),0) -> 0.098039216
A5: Avg Tenure | B5: =IFERROR(AVERAGE(H6:H205),0) -> 9.144
A6: Emp ID | B6: Full Name | C6: Job Title | D6: Department | E6: Location | F6: Salary ($) | G6: Age | H6: Tenure (Yrs) | I6: Perf Score | J6: Gender | K6: Status | L6: Hire Date | M6: Last Review | N6: Manager
A7: EMP1001 | B7: John Johnson | C7: Sales Rep | D7: Sales | E7: Chicago | F7: 113598 | G7: 40 | H7: 4.8 | I7: 3 | J7: Male | K7: Active | L7: 44442 | M7: 45944 | N7: Michael Chen
A8: EMP1002 | B8: James Carter | C8: FP&A Manager | D8: Finance | E8: Miami | F8: 109453 | G8: 24 | H8: 10.3 | I8: 4 | J8: Non-Binary | K8: Active | L8: 42109 | M8: 45939 | N8: Emily Davis
A9: EMP1003 | B9: Thomas Williams | C9: Process Specialist | D9: Operations | E9: San Francisco | F9: 68189 | G9: 36 | H9: 17.3 | I9: 3 | J9: Male | K9: Active | L9: 39627 | M9: 45828 | N9: James Brown
A10: EMP1004 | B10: Joseph Roberts | C10: Paralegal | D10: Legal | E10: San Francisco | F10: 116178 | G10: 41 | H10: 15 | I10: 4 | J10: Female | K10: Active | L10: 40515 | M10: 45679 | N10: Lisa Thompson
A11: EMP1005 | B11: Melissa Adams | C11: Financial Analyst | D11: Finance | E11: Austin | F11: 94911 | G11: 40 | H11: 8.4 | I11: 4 | J11: Male | K11: Active | L11: 42847 | M11: 45800 | N11: Michael Chen
A12: EMP1006 | B12: John Lee | C12: Senior Analyst | D12: Finance | E12: Boston | F12: 100294 | G12: 47 | H12: 5.2 | I12: 5 | J12: Non-Binary | K12: Active | L12: 44146 | M12: 45665 | N12: Amanda Wilson
A13: EMP1007 | B13: Donna Wright | C13: Account Executive | D13: Sales | E13: Miami | F13: 102170 | G13: 43 | H13: 4.2 | I13: 3 | J13: Non-Binary | K13: Active | L13: 44321 | M13: 45771 | N13: Lisa Thompson
A14: EMP1008 | B14: Melissa Ramirez | C14: Associate GC | D14: Legal | E14: Miami | F14: 94373 | G14: 31 | H14: 9.4 | I14: 2 | J14: Male | K14: Inactive | L14: 42450 | M14: 45742 | N14: Michael Chen
A15: EMP1009 | B15: Karen Roberts | C15: Legal Analyst | D15: Legal | E15: San Francisco | F15: 110674 | G15: 56 | H15: 4.9 | I15: 4 | J15: Male | K15: Active | L15: 44249 | M15: 45925 | N15: David Martinez
A16: EMP1010 | B16: Michael Green | C16: Brand Manager | D16: Marketing | E16: Chicago | F16: 70365 | G16: 52 | H16: 0.6 | I16: 4 | J16: Non-Binary | K16: Active | L16: 45925 | M16: 45733 | N16: Lisa Thompson
A17: EMP1011 | B17: Patricia White | C17: Recruiter | D17: HR | E17: Chicago | F17: 104971 | G17: 33 | H17: 9.9 | I17: 4 | J17: Non-Binary | K17: Inactive | L17: 42654 | M17: 45870 | N17: Lisa Thompson
A18: EMP1012 | B18: Brian Walker | C18: Senior Engineer | D18: Engineering | E18: Boston | F18: 122182 | G18: 28 | H18: 2 | I18: 3 | J18: Male | K18: Inactive | L18: 45194 | M18: 45721 | N18: Emily Davis
... A56: EMP1050 | B56: Ronald King | C56: Finance Manager | D56: Finance | E56: San Francisco | F56: 77835 | G56: 57 | H56: 17.1 | I56: 4 | J56: Male | K56: Active | L56: 39669 | M56: 46010 | N56: Lisa Thompson

Sheet 📋 Recruitment
A1: 📋 RECRUITMENT PIPELINE TRACKER
A3: Open Positions | B3: =COUNTIF(E7:E56,"Open") -> 23 | C3: Applications Received | D3: =COUNTA(A7:A56) -> 30 | E3: Interviews Scheduled | F3: =COUNTIF(H7:H56,"Scheduled")+COUNTIF(H7:H56,"Completed") -> 0 | G3: Offers Extended | H3: =COUNTIF(H7:H56,"Offer Extended")+COUNTIF(H7:H56,"Hired") -> 8 | I3: Avg Days to Hire | J3: =IFERROR(AVERAGEIF(H7:H56,"Hired",K7:K56),0) -> 51
A5: HIRING FUNNEL: Applications → Screened → Interviewed → Offers → Hired
A6: Req ID | B6: Position Title | C6: Department | D6: Hiring Manager | E6: Status | F6: Priority | G6: Posted Date | H6: Stage | I6: Candidate Name | J6: Candidate Email | K6: Days Open | L6: Days to Hire
A7: REQ2001 | B7: Treasury Analyst | C7: Finance | D7: Michael Chen | E7: Open | F7: Medium | G7: 45767 | H7: Phone Screen | I7: Sarah Rodriguez | J7: sarah.rodriguez@email.com | K7: 34
A8: REQ2002 | B8: Systems Engineer | C8: IT | D8: Robert Kim | E8: Closed | F8: Medium | G8: 45922 | H8: Hired | I8: Carol Young | J8: carol.young@email.com | K8: 73 | L8: 25
A9: REQ2003 | B9: Network Admin | C9: IT | D9: Emily Davis | E9: Open | F9: Low | G9: 45835 | H9: Panel Interview | I9: Jennifer Robinson | J9: jennifer.robinson@email.com | K9: 32
A10: REQ2004 | B10: HR Business Partner | C10: HR | D10: Sarah Johnson | E10: Closed | F10: Medium | G10: 46008 | H10: Hired | I10: Christopher Sanchez | J10: christopher.sanchez@email.com | K10: 16 | L10: 50
A11: REQ2005 | B11: Growth Marketer | C11: Marketing | D11: Robert Kim | E11: Open | F11: Low | G11: 45845 | H11: Technical Interview | I11: Barbara Robinson | J11: barbara.robinson@email.com | K11: 73
A12: REQ2006 | B12: Financial Analyst | C12: Finance | D12: Emily Davis | E12: Open | F12: Low | G12: 45813 | H12: Phone Screen | I12: Stephanie Lewis | J12: stephanie.lewis@email.com | K12: 25
A13: REQ2007 | B13: Network Admin | C13: IT | D13: Amanda Wilson | E13: Open | F13: High | G13: 45661 | H13: Applied | I13: Donald Baker | J13: donald.baker@email.com | K13: 26
A14: REQ2008 | B14: Financial Analyst | C14: Finance | D14: Emily Davis | E14: Open | F14: Low | G14: 45726 | H14: Offer Extended | I14: Matthew Perez | J14: matthew.perez@email.com | K14: 5
A15: REQ2009 | B15: Senior Accountant | C15: Finance | D15: Amanda Wilson | E15: Open | F15: High | G15: 45678 | H15: Phone Screen | I15: Thomas Wright | J15: thomas.wright@email.com | K15: 61
A16: REQ2010 | B16: HRIS Analyst | C16: HR | D16: Amanda Wilson | E16: Closed | F16: High | G16: 45662 | H16: Hired | I16: Stephanie Martinez | J16: stephanie.martinez@email.com | K16: 81 | L16: 69
A17: REQ2011 | B17: Senior Software Engineer | C17: Engineering | D17: Robert Kim | E17: Open | F17: Low | G17: 45726 | H17: Phone Screen | I17: Anthony Martinez | J17: anthony.martinez@email.com | K17: 27
A18: REQ2012 | B18: HRIS Analyst | C18: HR | D18: Michael Chen | E18: Open | F18: Low | G18: 45775 | H18: Technical Interview | I18: Betty Lopez | J18: betty.lopez@email.com | K18: 20
A19: REQ2013 | B19: HR Business Partner | C19: HR | D19: Amanda Wilson | E19: Open | F19: Medium | G19: 45957 | H19: Applied | I19: Jessica Harris | J19: jessica.harris@email.com | K19: 48
A20: REQ2014 | B20: Treasury Analyst | C20: Finance | D20: Sarah Johnson | E20: Open | F20: Medium | G20: 45865 | H20: Technical Interview | I20: Barbara Lopez | J20: barbara.lopez@email.com | K20: 73
A21: REQ2015 | B21: Systems Engineer | C21: IT | D21: Lisa Thompson | E21: Open | F21: High | G21: 45877 | H21: Technical Interview | I21: Joseph Adams | J21: joseph.adams@email.com | K21: 88
A22: REQ2016 | B22: IT Security Analyst | C22: IT | D22: James Brown | E22: Closed | F22: High | G22: 45772 | H22: Rejected | I22: Matthew Jackson | J22: matthew.jackson@email.com | K22: 36
A23: REQ2017 | B23: Treasury Analyst | C23: Finance | D23: James Brown | E23: Open | F23: Low | G23: 45780 | H23: Offer Extended | I23: Melissa Lee | J23: melissa.lee@email.com | K23: 42
A24: REQ2018 | B24: SDR | C24: Sales | D24: Lisa Thompson | E24: Open | F24: Medium | G24: 45848 | H24: Panel Interview | I24: Carol Hernandez | J24: carol.hernandez@email.com | K24: 89
A25: REQ2019 | B25: Systems Engineer | C25: IT | D25: David Martinez | E25: Open | F25: Low | G25: 45760 | H25: Technical Interview | I25: Daniel Smith | J25: daniel.smith@email.com | K25: 30
A26: REQ2020 | B26: Recruiter | C26: HR | D26: Amanda Wilson | E26: Open | F26: Low | G26: 45983 | H26: Phone Screen | I26: Thomas Nelson | J26: thomas.nelson@email.com | K26: 86
A27: REQ2021 | B27: Network Admin | C27: IT | D27: Sarah Johnson | E27: Closed | F27: High | G27: 45866 | H27: Rejected | I27: Brian Sanchez | J27: brian.sanchez@email.com | K27: 49
A28: REQ2022 | B28: Content Strategist | C28: Marketing | D28: Robert Kim | E28: Open | F28: Medium | G28: 45674 | H28: Technical Interview | I28: Paul Lewis | J28: paul.lewis@email.com | K28: 26
... A30: REQ2024 | B30: Cloud Architect | C30: IT | D30: Sarah Johnson | E30: Open | F30: Medium | G30: 45714 | H30: Technical Interview | I30: Michelle Williams | J30: michelle.williams@email.com | K30: 14
A31: REQ2025 | B31: Compensation Manager | C31: HR | D31: Michael Chen | E31: Closed | F31: Medium | G31: 45921 | H31: Hired | I31: Charles Gonzalez | J31: charles.gonzalez@email.com | K31: 80 | L31: 56
A32: REQ2026 | B32: Senior Accountant | C32: Finance | D32: Amanda Wilson | E32: Open | F32: Medium | G32: 45792 | H32: Technical Interview | I32: William Lewis | J32: william.lewis@email.com | K32: 21
A33: REQ2027 | B33: Content Strategist | C33: Marketing | D33: Amanda Wilson | E33: Open | F33: High | G33: 45817 | H33: Phone Screen | I33: Ashley Torres | J33: ashley.torres@email.com | K33: 40
A34: REQ2028 | B34: Treasury Analyst | C34: Finance | D34: Sarah Johnson | E34: Open | F34: High | G34: 45967 | H34: Applied | I34: Sarah Robinson | J34: sarah.robinson@email.com | K34: 73
A35: REQ2029 | B35: HRIS Analyst | C35: HR | D35: Lisa Thompson | E35: Closed | F35: Low | G35: 45699 | H35: Hired | I35: Melissa Wright | J35: melissa.wright@email.com | K35: 5 | L35: 56
A36: REQ2030 | B36: ML Engineer | C36: Engineering | D36: Amanda Wilson | E36: Open | F36: High | G36: 45847 | H36: Phone Screen | I36: Michelle Brown | J36: michelle.brown@email.com | K36: 22

Sheet ⭐ Performance
A1: ⭐ PERFORMANCE REVIEW & GOAL TRACKER
A3: Emp ID | B3: Employee Name | C3: Department | D3: Review Period | E3: Manager | F3: Goal 1 Score | G3: Goal 2 Score | H3: Goal 3 Score | I3: Avg Goal Score | J3: Competency Score | K3: Overall Rating | L3: Raise % | M3: Bonus ($) | N3: Review Status
A4: EMP1001 | B4: Christopher Gonzalez | C4: Marketing | D4: Annual 2024 | E4: Robert Kim | F4: 2.7 | G4: 4.5 | H4: 2.3 | I4: =AVERAGE(F4:H4) -> 3.1666667 | J4: 3.4 | K4: =ROUND((AVERAGE(F4:H4)*0.6+J4*0.4),1) -> 3.3 | L4: =IFERROR(IF(K4>=4.5,0.08,IF(K4>=3.5,0.05,IF(K4>=2.5,0.03,0))),0) -> 0.03 | M4: =IFERROR(IF(K4>=4.5,L4*VLOOKUP(C4,salary_ref,2,0)*0.15,IF(K4>=3.5,L4*VLOOKUP(C4,salary_ref,2,0)*0.1,0)),"N/A") -> 0 | N4: In Progress
A5: EMP1002 | B5: Karen Johnson | C5: Engineering | D5: Q4 2025 | E5: Emily Davis | F5: 4.5 | G5: 3.5 | H5: 4.4 | I5: =AVERAGE(F5:H5) -> 4.1333333 | J5: 2.6 | K5: =ROUND((AVERAGE(F5:H5)*0.6+J5*0.4),1) -> 3.5 | L5: =IFERROR(IF(K5>=4.5,0.08,IF(K5>=3.5,0.05,IF(K5>=2.5,0.03,0))),0) -> 0.05 | M5: =IFERROR(IF(K5>=4.5,L5*VLOOKUP(C5,salary_ref,2,0)*0.15,IF(K5>=3.5,L5*VLOOKUP(C5,salary_ref,2,0)*0.1,0)),"N/A") -> N/A | N5: Pending
A6: EMP1003 | B6: Patricia Garcia | C6: Operations | D6: Q1 2025 | E6: Michael Chen | F6: 3.7 | G6: 2.8 | H6: 3.4 | I6: =AVERAGE(F6:H6) -> 3.3 | J6: 2.7 | K6: =ROUND((AVERAGE(F6:H6)*0.6+J6*0.4),1) -> 3.1 | L6: =IFERROR(IF(K6>=4.5,0.08,IF(K6>=3.5,0.05,IF(K6>=2.5,0.03,0))),0) -> 0.03 | M6: =IFERROR(IF(K6>=4.5,L6*VLOOKUP(C6,salary_ref,2,0)*0.15,IF(K6>=3.5,L6*VLOOKUP(C6,salary_ref,2,0)*0.1,0)),"N/A") -> 0 | N6: In Progress
A7: EMP1004 | B7: Kenneth Rivera | C7: IT | D7: Q2 2025 | E7: David Martinez | F7: 3.6 | G7: 2.3 | H7: 4.4 | I7: =AVERAGE(F7:H7) -> 3.4333333 | J7: 4.1 | K7: =ROUND((AVERAGE(F7:H7)*0.6+J7*0.4),1) -> 3.7 | L7: =IFERROR(IF(K7>=4.5,0.08,IF(K7>=3.5,0.05,IF(K7>=2.5,0.03,0))),0) -> 0.05 | M7: =IFERROR(IF(K7>=4.5,L7*VLOOKUP(C7,salary_ref,2,0)*0.15,IF(K7>=3.5,L7*VLOOKUP(C7,salary_ref,2,0)*0.1,0)),"N/A") -> N/A | N7: Completed
A8: EMP1005 | B8: Andrew Robinson | C8: Sales | D8: Q3 2025 | E8: James Brown | F8: 4.5 | G8: 4.8 | H8: 4.4 | I8: =AVERAGE(F8:H8) -> 4.5666667 | J8: 4.9 | K8: =ROUND((AVERAGE(F8:H8)*0.6+J8*0.4),1) -> 4.7 | L8: =IFERROR(IF(K8>=4.5,0.08,IF(K8>=3.5,0.05,IF(K8>=2.5,0.03,0))),0) -> 0.08 | M8: =IFERROR(IF(K8>=4.5,L8*VLOOKUP(C8,salary_ref,2,0)*0.15,IF(K8>=3.5,L8*VLOOKUP(C8,salary_ref,2,0)*0.1,0)),"N/A") -> N/A | N8: Completed
A9: EMP1006 | B9: Emily Brown | C9: Operations | D9: Annual 2024 | E9: Robert Kim | F9: 4.5 | G9: 4.3 | H9: 3.2 | I9: =AVERAGE(F9:H9) -> 4 | J9: 3.7 | K9: =ROUND((AVERAGE(F9:H9)*0.6+J9*0.4),1) -> 3.9 | L9: =IFERROR(IF(K9>=4.5,0.08,IF(K9>=3.5,0.05,IF(K9>=2.5,0.03,0))),0) -> 0.05 | M9: =IFERROR(IF(K9>=4.5,L9*VLOOKUP(C9,salary_ref,2,0)*0.15,IF(K9>=3.5,L9*VLOOKUP(C9,salary_ref,2,0)*0.1,0)),"N/A") -> N/A | N9: In Progress
A10: EMP1007 | B10: Margaret Mitchell | C10: IT | D10: Q1 2025 | E10: James Brown | F10: 2.4 | G10: 4.4 | H10: 2 | I10: =AVERAGE(F10:H10) -> 2.9333333 | J10: 5 | K10: =ROUND((AVERAGE(F10:H10)*0.6+J10*0.4),1) -> 3.8 | L10: =IFERROR(IF(K10>=4.5,0.08,IF(K10>=3.5,0.05,IF(K10>=2.5,0.03,0))),0) -> 0.05 | M10: =IFERROR(IF(K10>=4.5,L10*VLOOKUP(C10,salary_ref,2,0)*0.15,IF(K10>=3.5,L10*VLOOKUP(C10,salary_ref,2,0)*0.1,0)),"N/A") -> N/A | N10: Completed
A11: EMP1008 | B11: Ronald Ramirez | C11: Operations | D11: Q1 2025 | E11: James Brown | F11: 2.4 | G11: 5 | H11: 4.7 | I11: =AVERAGE(F11:H11) -> 4.0333333 | J11: 4.1 | K11: =ROUND((AVERAGE(F11:H11)*0.6+J11*0.4),1) -> 4.1 | L11: =IFERROR(IF(K11>=4.5,0.08,IF(K11>=3.5,0.05,IF(K11>=2.5,0.03,0))),0) -> 0.05 | M11: =IFERROR(IF(K11>=4.5,L11*VLOOKUP(C11,salary_ref,2,0)*0.15,IF(K11>=3.5,L11*VLOOKUP(C11,salary_ref,2,0)*0.1,0)),"N/A") -> N/A | N11: Completed
A12: EMP1009 | B12: Nancy King | C12: HR | D12: Q4 2025 | E12: Sarah Johnson | F12: 2.3 | G12: 4.5 | H12: 4.7 | I12: =AVERAGE(F12:H12) -> 3.8333333 | J12: 4.8 | K12: =ROUND((AVERAGE(F12:H12)*0.6+J12*0.4),1) -> 4.2 | L12: =IFERROR(IF(K12>=4.5,0.08,IF(K12>=3.5,0.05,IF(K12>=2.5,0.03,0))),0) -> 0.05 | M12: =IFERROR(IF(K12>=4.5,L12*VLOOKUP(C12,salary_ref,2,0)*0.15,IF(K12>=3.5,L12*VLOOKUP(C12,salary_ref,2,0)*0.1,0)),"N/A") -> N/A | N12: Completed
A13: EMP1010 | B13: Jennifer Carter | C13: IT | D13: Q4 2025 | E13: Michael Chen | F13: 4.5 | G13: 4.7 | H13: 4.1 | I13: =AVERAGE(F13:H13) -> 4.4333333 | J13: 2.7 | K13: =ROUND((AVERAGE(F13:H13)*0.6+J13*0.4),1) -> 3.7 | L13: =IFERROR(IF(K13>=4.5,0.08,IF(K13>=3.5,0.05,IF(K13>=2.5,0.03,0))),0) -> 0.05 | M13: =IFERROR(IF(K13>=4.5,L13*VLOOKUP(C13,salary_ref,2,0)*0.15,IF(K13>=3.5,L13*VLOOKUP(C13,salary_ref,2,0)*0.1,0)),"N/A") -> N/A | N13: Not Started
A14: EMP1011 | B14: Michael Rodriguez | C14: IT | D14: Q2 2025 | E14: Sarah Johnson | F14: 2.7 | G14: 2.6 | H14: 4.5 | I14: =AVERAGE(F14:H14) -> 3.2666667 | J14: 2.5 | K14: =ROUND((AVERAGE(F14:H14)*0.6+J14*0.4),1) -> 3 | L14: =IFERROR(IF(K14>=4.5,0.08,IF(K14>=3.5,0.05,IF(K14>=2.5,0.03,0))),0) -> 0.03 | M14: =IFERROR(IF(K14>=4.5,L14*VLOOKUP(C14,salary_ref,2,0)*0.15,IF(K14>=3.5,L14*VLOOKUP(C14,salary_ref,2,0)*0.1,0)),"N/A") -> 0 | N14: Completed
A15: EMP1012 | B15: Brian Allen | C15: Finance | D15: Q4 2025 | E15: James Brown | F15: 4.3 | G15: 4.9 | H15: 3.7 | I15: =AVERAGE(F15:H15) -> 4.3 | J15: 4.2 | K15: =ROUND((AVERAGE(F15:H15)*0.6+J15*0.4),1) -> 4.3 | L15: =IFERROR(IF(K15>=4.5,0.08,IF(K15>=3.5,0.05,IF(K15>=2.5,0.03,0))),0) -> 0.05 | M15: =IFERROR(IF(K15>=4.5,L15*VLOOKUP(C15,salary_ref,2,0)*0.15,IF(K15>=3.5,L15*VLOOKUP(C15,salary_ref,2,0)*0.1,0)),"N/A") -> N/A | N15: Pending
... A43: EMP1040 | B43: Ronald Davis | C43: Finance | D43: Q4 2025 | E43: James Brown | F43: 3.9 | G43: 3.5 | H43: 3.7 | I43: =AVERAGE(F43:H43) -> 3.7 | J43: 2.5 | K43: =ROUND((AVERAGE(F43:H43)*0.6+J43*0.4),1) -> 3.2 | L43: =IFERROR(IF(K43>=4.5,0.08,IF(K43>=3.5,0.05,IF(K43>=2.5,0.03,0))),0) -> 0.03 | M43: =IFERROR(IF(K43>=4.5,L43*VLOOKUP(C43,salary_ref,2,0)*0.15,IF(K43>=3.5,L43*VLOOKUP(C43,salary_ref,2,0)*0.1,0)),"N/A") -> 0 | N43: Not Started

Sheet 💰 Payroll
A1: 💰 PAYROLL & COMPENSATION SUMMARY
A3: Emp ID | B3: Full Name | C3: Department | D3: Base Salary | E3: Federal Tax | F3: State Tax | G3: Social Security | H3: Medicare | I3: Health Insurance | J3: Net Pay | K3: Pay Period | L3: Pay Date
A4: EMP1001 | B4: Barbara Gonzalez | C4: HR | D4: 94673 | E4: =D4*0.22 -> 20828.06 | F4: =D4*0.05 -> 4733.65 | G4: =MIN(D4*0.062,9114) -> 5869.726 | H4: =D4*0.0145 -> 1372.7585 | I4: 3600 | J4: =D4-E4-F4-G4-H4-I4 -> 58268.806 | K4: Bi-Weekly | L4: 46006
A5: EMP1002 | B5: Nancy Garcia | C5: Operations | D5: 141851 | E5: =D5*0.22 -> 31207.22 | F5: =D5*0.05 -> 7092.55 | G5: =MIN(D5*0.062,9114) -> 8794.762 | H5: =D5*0.0145 -> 2056.8395 | I5: 3600 | J5: =D5-E5-F5-G5-H5-I5 -> 89099.629 | K5: Monthly | L5: 46021
A6: EMP1003 | B6: Matthew Allen | C6: Legal | D6: 96711 | E6: =D6*0.22 -> 21276.42 | F6: =D6*0.05 -> 4835.55 | G6: =MIN(D6*0.062,9114) -> 5996.082 | H6: =D6*0.0145 -> 1402.3095 | I6: 3600 | J6: =D6-E6-F6-G6-H6-I6 -> 59600.639 | K6: Semi-Monthly | L6: 46021
A7: EMP1004 | B7: Steven Roberts | C7: Engineering | D7: 137905 | E7: =D7*0.22 -> 30339.1 | F7: =D7*0.05 -> 6895.25 | G7: =MIN(D7*0.062,9114) -> 8550.11 | H7: =D7*0.0145 -> 1999.6225 | I7: 3600 | J7: =D7-E7-F7-G7-H7-I7 -> 86520.917 | K7: Monthly | L7: 46006
A8: EMP1005 | B8: Joseph Allen | C8: Engineering | D8: 129756 | E8: =D8*0.22 -> 28546.32 | F8: =D8*0.05 -> 6487.8 | G8: =MIN(D8*0.062,9114) -> 8044.872 | H8: =D8*0.0145 -> 1881.462 | I8: 3600 | J8: =D8-E8-F8-G8-H8-I8 -> 81195.546 | K8: Monthly | L8: 46006
A9: EMP1006 | B9: Linda Harris | C9: Finance | D9: 66610 | E9: =D9*0.22 -> 14654.2 | F9: =D9*0.05 -> 3330.5 | G9: =MIN(D9*0.062,9114) -> 4129.82 | H9: =D9*0.0145 -> 965.845 | I9: 3600 | J9: =D9-E9-F9-G9-H9-I9 -> 39929.635 | K9: Semi-Monthly | L9: 46021
A10: EMP1007 | B10: Richard Anderson | C10: Finance | D10: 108791 | E10: =D10*0.22 -> 23934.02 | F10: =D10*0.05 -> 5439.55 | G10: =MIN(D10*0.062,9114) -> 6745.042 | H10: =D10*0.0145 -> 1577.4695 | I10: 3600 | J10: =D10-E10-F10-G10-H10-I10 -> 67494.918 | K10: Bi-Weekly | L10: 46021
A11: EMP1008 | B11: Lisa Smith | C11: Sales | D11: 108760 | E11: =D11*0.22 -> 23927.2 | F11: =D11*0.05 -> 5438 | G11: =MIN(D11*0.062,9114) -> 6743.12 | H11: =D11*0.0145 -> 1577.02 | I11: 3600 | J11: =D11-E11-F11-G11-H11-I11 -> 67474.66 | K11: Monthly | L11: 46021
A12: EMP1009 | B12: Betty Flores | C12: Finance | D12: 86519 | E12: =D12*0.22 -> 19034.18 | F12: =D12*0.05 -> 4325.95 | G12: =MIN(D12*0.062,9114) -> 5364.178 | H12: =D12*0.0145 -> 1254.5255 | I12: 3600 | J12: =D12-E12-F12-G12-H12-I12 -> 52940.166 | K12: Monthly | L12: 46006
A13: EMP1010 | B13: David Anderson | C13: Marketing | D13: 127617 | E13: =D13*0.22 -> 28075.74 | F13: =D13*0.05 -> 6380.85 | G13: =MIN(D13*0.062,9114) -> 7912.254 | H13: =D13*0.0145 -> 1850.4465 | I13: 3600 | J13: =D13-E13-F13-G13-H13-I13 -> 79797.709 | K13: Bi-Weekly | L13: 46021
A14: EMP1011 | B14: Jessica Martin | C14: HR | D14: 109409 | E14: =D14*0.22 -> 24069.98 | F14: =D14*0.05 -> 5470.45 | G14: =MIN(D14*0.062,9114) -> 6783.358 | H14: =D14*0.0145 -> 1586.4305 | I14: 3600 | J14: =D14-E14-F14-G14-H14-I14 -> 67898.781 | K14: Monthly | L14: 46006
A15: EMP1012 | B15: Margaret Nelson | C15: Sales | D15: 88332 | E15: =D15*0.22 -> 19433.04 | F15: =D15*0.05 -> 4416.6 | G15: =MIN(D15*0.062,9114) -> 5476.584 | H15: =D15*0.0145 -> 1280.814 | I15: 3600 | J15: =D15-E15-F15-G15-H15-I15 -> 54124.962 | K15: Bi-Weekly | L15: 46021
... A43: EMP1040 | B43: Kimberly Sanchez | C43: Engineering | D43: 98602 | E43: =D43*0.22 -> 21692.44 | F43: =D43*0.05 -> 4930.1 | G43: =MIN(D43*0.062,9114) -> 6113.324 | H43: =D43*0.0145 -> 1429.729 | I43: 3600 | J43: =D43-E43-F43-G43-H43-I43 -> 60836.407 | K43: Monthly | L43: 46006
A44: TOTALS | D44: =SUM(D4:D43) -> 3951411 | E44: =SUM(E4:E43) -> 869310.42 | F44: =SUM(F4:F43) -> 197570.55 | G44: =SUM(G4:G43) -> 244987.48 | H44: =SUM(H4:H43) -> 57295.459 | I44: =SUM(I4:I43) -> 144000 | J44: =SUM(J4:J43) -> 2438247.1

Sheet 📈 Forecast
A1: 📈 HEADCOUNT & BUDGET FORECAST | 2025–2027
A3: KEY ASSUMPTIONS
A4: Headcount Growth Rate | B4: 0.12
A5: Attrition Rate | B5: 0.08
A6: Avg Salary Increase | B6: 0.045
A7: Hiring Cost per Head | B7: 8500
A8: Benefits % of Salary | B8: 0.22
A10: Metric | B10: 2024 (Actual) | C10: 2025 Q1 | D10: 2025 Q2 | E10: 2025 Q3 | F10: 2025 Q4 | G10: 2026 Q1 | H10: 2026 Q2 | I10: 2026 Q3 | J10: 2026 Q4 | K10: 2027 Q1 | L10: 2027 Q2 | M10: 2027 Q3 | N10: 2027 Q4
A11: Headcount (EOP) | B11: 50 | C11: 52 | D11: 55 | E11: 57 | F11: 59 | G11: 62 | H11: 65 | I11: 68 | J11: 71 | K11: 74 | L11: 78 | M11: 82 | N11: 86
A12: New Hires | B12: 0 | C12: 2 | D12: 3 | E12: 2 | F12: 2 | G12: 3 | H12: 3 | I12: 3 | J12: 3 | K12: 3 | L12: 4 | M12: 4 | N12: 4
A13: Attritions | B13: 0 | C13: 0 | D13: 0 | E13: 0 | F13: 2 | G13: 1 | H13: 0 | I13: 0 | J13: 1 | K13: 1 | L13: 0 | M13: 0 | N13: 1
A14: Total Salary Budget($) | B14: 4250000 | C14: 4420000 | D14: 4675000 | E14: 4845000 | F14: 5015000 | G14: 5270000 | H14: 5525000 | I14: 5780000 | J14: 6035000 | K14: 6290000 | L14: 6630000 | M14: 6970000 | N14: 7310000
A15: Hiring Costs ($) | B15: =C12*$B$7 -> 17000 | C15: =C12*$B$7 -> 17000 | D15: =C12*$B$7 -> 17000 | E15: =C12*$B$7 -> 17000 | F15: =C12*$B$7 -> 17000 | G15: =C12*$B$7 -> 17000 | H15: =C12*$B$7 -> 17000 | I15: =C12*$B$7 -> 17000 | J15: =C12*$B$7 -> 17000 | K15: =C12*$B$7 -> 17000 | L15: =C12*$B$7 -> 17000 | M15: =C12*$B$7 -> 17000 | N15: =C12*$B$7 -> 17000
A16: Benefits Cost ($) | B16: =B14*$B$8 -> 935000 | C16: =C14*$B$8 -> 972400 | D16: =D14*$B$8 -> 1028500 | E16: =E14*$B$8 -> 1065900 | F16: =F14*$B$8 -> 1103300 | G16: =G14*$B$8 -> 1159400 | H16: =H14*$B$8 -> 1215500 | I16: =I14*$B$8 -> 1271600 | ... N16: =N14*$B$8 -> 1608200
A17: Total People Cost ($) | B17: =B14+B15+B16 -> 5202000 | C17: =C14+C15+C16 -> 5409400 | D17: =D14+D15+D16 -> 5720500 | E17: =E14+E15+E16 -> 5927900 | F17: =F14+F15+F16 -> 6135300 | G17: =G14+G15+G16 -> 6446400 | H17: =H14+H15+H16 -> 6757500 | I17: =I14+I15+I16 -> 7068600 | ... N17: =N14+N15+N16 -> 8935200

Sheet 🎓 Training
A1: 🎓 LEARNING & DEVELOPMENT TRACKER
A3: Emp ID | B3: Employee Name | C3: Department | D3: Course Name | E3: Category | F3: Provider | G3: Start Date | H3: End Date | I3: Hours | J3: Status | K3: Score (%) | L3: Certification
A4: EMP1001 | B4: Kevin Anderson | C4: HR | D4: SQL for Business | E4: Soft Skills | F4: Pluralsight | G4: 45793 | H4: 45901 | I4: 22 | J4: In Progress | L4: No
A5: EMP1002 | B5: Mark Jackson | C5: IT | D5: Financial Modeling | E5: Certification | F5: Pluralsight | G5: 45982 | H5: 46000 | I5: 33 | J5: Not Started | L5: No
A6: EMP1003 | B6: Stephanie Hill | C6: Engineering | D6: Agile & Scrum | E6: Leadership | F6: Coursera | G6: 45975 | H6: 46032 | I6: 5 | J6: Not Started | L6: No
A7: EMP1004 | B7: Charles Wilson | C7: Operations | D7: Project Management Basics | E7: Leadership | F7: Pluralsight | G7: 45712 | H7: 45787 | I7: 19 | J7: Completed | K7: 82 | L7: Yes
A8: EMP1005 | B8: James Thompson | C8: Operations | D8: Financial Modeling | E8: Leadership | F8: Harvard Online | G8: 45922 | H8: 45985 | I8: 9 | J8: Enrolled | L8: No
A9: EMP1006 | B9: Betty Green | C9: Engineering | D9: Leadership Essentials | E9: Technical | F9: Udemy | G9: 45979 | H9: 46006 | I9: 2 | J9: Completed | K9: 71 | L9: Yes
A10: EMP1007 | B10: Anthony Moore | C10: Engineering | D10: Data Privacy & GDPR | E10: Soft Skills | F10: Internal | G10: 45815 | H10: 45857 | I10: 24 | J10: Enrolled | L10: No
A11: EMP1008 | B11: Nancy Young | C11: IT | D11: Financial Modeling | E11: Certification | F11: Coursera | G11: 45689 | H11: 45785 | I11: 17 | J11: Enrolled | L11: No
A12: EMP1009 | B12: Steven Green | C12: Engineering | D12: Cybersecurity Fundamentals | E12: Compliance | F12: Harvard Online | G12: 45893 | H12: 45959 | I12: 32 | J12: In Progress | L12: No
A13: EMP1010 | B13: George Garcia | C13: Engineering | D13: AWS Cloud Practitioner | E13: Compliance | F13: Pluralsight | G13: 45954 | H13: 46014 | I13: 28 | J13: Enrolled | L13: No
A14: EMP1011 | B14: Donald Flores | C14: Marketing | D14: Conflict Resolution | E14: Certification | F14: LinkedIn Learning | G14: 45882 | H14: 45891 | I14: 8 | J14: Enrolled | L14: No
A15: EMP1012 | B15: Deborah Lee | C15: HR | D15: Google Analytics | E15: Compliance | F15: Internal | G15: 45940 | H15: 45979 | I15: 23 | J15: Not Started | L15: No
A16: EMP1013 | B16: Ronald Nguyen | C16: Operations | D16: Data Privacy & GDPR | E16: Technical | F16: Udemy | G16: 45978 | H16: 45990 | I16: 39 | J16: Completed | K16: 76 | L16: Yes
A17: EMP1014 | B17: Andrew Davis | C17: Sales | D17: Excel Macros & VBA | E17: Technical | F17: Coursera | G17: 45775 | H17: 45817 | I17: 2 | J17: In Progress | L17: No
A18: EMP1015 | B18: Emily Baker | C18: Legal | D18: Python for Data Analysis | E18: Technical | F18: LinkedIn Learning | G18: 45809 | H18: 45842 | I18: 31 | J18: Enrolled | L18: No
A19: EMP1016 | B19: Dorothy Johnson | C19: Engineering | D19: SQL for Business | E19: Technical | F19: Udemy | G19: 45955 | H19: 46000 | I19: 25 | J19: In Progress | L19: No
A20: EMP1017 | B20: Stephanie Young | C20: Sales | D20: Google Analytics | E20: Certification | F20: Pluralsight | G20: 45778 | H20: 45787 | I20: 23 | J20: Completed | K20: 93 | L20: Yes
A21: EMP1018 | B21: Emily Rodriguez | C21: Operations | D21: Data Privacy & GDPR | E21: Compliance | F21: Udemy | G21: 45812 | H21: 45881 | I21: 14 | J21: Enrolled | L21: No
A22: EMP1019 | B22: Emily Gonzalez | C22: Sales | D22: Financial Modeling | E22: Soft Skills | F22: LinkedIn Learning | G22: 45725 | H22: 45749 | I22: 10 | J22: In Progress | L22: No
A23: EMP1020 | B23: Steven Robinson | C23: IT | D23: Python for Data Analysis | E23: Technical | F23: LinkedIn Learning | G23: 45880 | H23: 45931 | I23: 23 | J23: Completed | K23: 63 | L23: No
A24: EMP1021 | B24: Betty Mitchell | C24: HR | D24: Data Privacy & GDPR | E24: Soft Skills | F24: Internal | G24: 45785 | H24: 45848 | I24: 38 | J24: Completed | K24: 93 | L24: Yes
A25: EMP1022 | B25: Timothy Moore | C25: Marketing | D25: PMP Certification | E25: Compliance | F25: Coursera | G25: 45772 | H25: 45784 | I25: 24 | J25: Not Started | L25: No
A26: EMP1023 | B26: Patricia Gonzalez | C26: Sales | D26: Project Management Basics | E26: Compliance | F26: Coursera | G26: 45974 | H26: 46043 | I26: 17 | J26: In Progress | L26: No
A27: EMP1024 | B27: Emily Hernandez | C27: HR | D27: Excel Advanced | E27: Leadership | F27: Internal | G27: 45858 | H27: 45876 | I27: 20 | J27: Enrolled | L27: No
A28: EMP1025 | B28: Timothy Harris | C28: Marketing | D28: Excel Macros & VBA | E28: Compliance | F28: Internal | G28: 45798 | H28: 45885 | I28: 30 | J28: In Progress | L28: No
A29: EMP1026 | B29: Michael White | C29: Legal | D29: Google Analytics | E29: Technical | F29: Coursera | G29: 45875 | H29: 45932 | I29: 12 | J29: In Progress | L29: No
A30: EMP1027 | B30: Matthew Perez | C30: HR | D30: Project Management Basics | E30: Leadership | F30: Coursera | G30: 45875 | H30: 45962 | I30: 10 | J30: In Progress | L30: No
A31: EMP1028 | B31: Jennifer Torres | C31: Legal | D31: Agile & Scrum | E31: Compliance | F31: Internal | G31: 45903 | H31: 45984 | I31: 2 | J31: Completed | K31: 98 | L31: Yes
A32: EMP1029 | B32: Mark Young | C32: Sales | D32: Agile & Scrum | E32: Soft Skills | F32: Internal | G32: 45764 | H32: 45827 | I32: 20 | J32: In Progress | L32: No
A33: EMP1030 | B33: Melissa Thomas | C33: IT | D33: PMP Certification | E33: Compliance | F33: Udemy | G33: 45847 | H33: 45853 | I33: 2 | J33: Not Started | L33: No
A34: EMP1031 | B34: Nancy Campbell | C34: Marketing | D34: AWS Cloud Practitioner | E34: Soft Skills | F34: Internal | G34: 45757 | H34: 45847 | I34: 34 | J34: Completed | K34: 77 | L34: Yes
A35: EMP1032 | B35: Daniel Hall | C35: Operations | D35: Conflict Resolution | E35: Leadership | F35: Pluralsight | G35: 45695 | H35: 45704 | I35: 19 | J35: Enrolled | L35: No
A36: EMP1033 | B36: Amanda Taylor | C36: Operations | D36: Project Management Basics | E36: Soft Skills | F36: LinkedIn Learning | G36: 45809 | H36: 45869 | I36: 3 | J36: Completed | K36: 73 | L36: Yes
A37: EMP1034 | B37: Linda Clark | C37: Marketing | D37: Google Analytics | E37: Soft Skills | F37: Harvard Online | G37: 45911 | H37: 45977 | I37: 24 | J37: Completed | K37: 89 | L37: Yes
A38: EMP1035 | B38: Daniel Thomas | C38: Marketing | D38: Diversity & Inclusion | E38: Technical | F38: Udemy | G38: 45677 | H38: 45683 | I38: 30 | J38: Enrolled | L38: No
